{"nodes":[{"id":"src_utils_taskutils_ts","label":"taskUtils","source_file":"./src/utils/taskUtils.ts","node_type":"file"},{"id":"src_utils_taskutils_ts_import_dayjs_dayjs","label":"dayjs/dayjs","source_file":"./src/utils/taskUtils.ts","source_location":"L1","node_type":"module"},{"id":"src_utils_taskutils_ts_import_types_task_task","label":"../types/task/Task","source_file":"./src/utils/taskUtils.ts","source_location":"L2","node_type":"module"},{"id":"src_utils_taskutils_ts_import_types_task_taskfilters","label":"../types/task/TaskFilters","source_file":"./src/utils/taskUtils.ts","source_location":"L2","node_type":"module"},{"id":"src_utils_taskutils_ts_import_types_task_taskpriorityfilter","label":"../types/task/TaskPriorityFilter","source_file":"./src/utils/taskUtils.ts","source_location":"L2","node_type":"module"},{"id":"src_utils_taskutils_ts_import_types_task_tasksortkey","label":"../types/task/TaskSortKey","source_file":"./src/utils/taskUtils.ts","source_location":"L2","node_type":"module"},{"id":"src_utils_taskutils_ts_import_types_task_taskstatusfilter","label":"../types/task/TaskStatusFilter","source_file":"./src/utils/taskUtils.ts","source_location":"L2","node_type":"module"},{"id":"src_utils_taskutils_ts_gettasktags","label":"getTaskTags()","source_file":"./src/utils/taskUtils.ts","source_location":"L16","node_type":"function"},{"id":"src_utils_taskutils_ts_filtertasks","label":"filterTasks()","source_file":"./src/utils/taskUtils.ts","source_location":"L24","node_type":"function"},{"id":"src_utils_taskutils_ts_sorttasks","label":"sortTasks()","source_file":"./src/utils/taskUtils.ts","source_location":"L40","node_type":"function"},{"id":"src_utils_taskutils_ts_grouptasksfortoday","label":"groupTasksForToday()","source_file":"./src/utils/taskUtils.ts","source_location":"L55","node_type":"function"},{"id":"src_utils_taskutils_ts_formattasktime","label":"formatTaskTime()","source_file":"./src/utils/taskUtils.ts","source_location":"L73","node_type":"function"},{"id":"src_utils_taskutils_ts_matchesstatusfilter","label":"matchesStatusFilter()","source_file":"./src/utils/taskUtils.ts","source_location":"L82","node_type":"function"},{"id":"src_utils_taskutils_ts_matchespriorityfilter","label":"matchesPriorityFilter()","source_file":"./src/utils/taskUtils.ts","source_location":"L86","node_type":"function"},{"id":"src_utils_taskutils_ts_compareoptionalnumber","label":"compareOptionalNumber()","source_file":"./src/utils/taskUtils.ts","source_location":"L90","node_type":"function"}],"edges":[{"source":"src_utils_taskutils_ts","target":"src_utils_taskutils_ts_import_dayjs_dayjs","relation":"imports","confidence":"EXTRACTED","confidence_score":1.0,"source_file":"./src/utils/taskUtils.ts","source_location":"L1","weight":1.0},{"source":"src_utils_taskutils_ts","target":"src_utils_taskutils_ts_import_types_task_task","relation":"imports","confidence":"EXTRACTED","confidence_score":1.0,"source_file":"./src/utils/taskUtils.ts","source_location":"L2","weight":1.0},{"source":"src_utils_taskutils_ts","target":"src_utils_taskutils_ts_import_types_task_taskfilters","relation":"imports","confidence":"EXTRACTED","confidence_score":1.0,"source_file":"./src/utils/taskUtils.ts","source_location":"L2","weight":1.0},{"source":"src_utils_taskutils_ts","target":"src_utils_taskutils_ts_import_types_task_taskpriorityfilter","relation":"imports","confidence":"EXTRACTED","confidence_score":1.0,"source_file":"./src/utils/taskUtils.ts","source_location":"L2","weight":1.0},{"source":"src_utils_taskutils_ts","target":"src_utils_taskutils_ts_import_types_task_tasksortkey","relation":"imports","confidence":"EXTRACTED","confidence_score":1.0,"source_file":"./src/utils/taskUtils.ts","source_location":"L2","weight":1.0},{"source":"src_utils_taskutils_ts","target":"src_utils_taskutils_ts_import_types_task_taskstatusfilter","relation":"imports","confidence":"EXTRACTED","confidence_score":1.0,"source_file":"./src/utils/taskUtils.ts","source_location":"L2","weight":1.0},{"source":"src_utils_taskutils_ts","target":"src_utils_taskutils_ts_gettasktags","relation":"defines","confidence":"EXTRACTED","confidence_score":1.0,"source_file":"./src/utils/taskUtils.ts","source_location":"L16","weight":1.0},{"source":"src_utils_taskutils_ts","target":"src_utils_taskutils_ts_filtertasks","relation":"defines","confidence":"EXTRACTED","confidence_score":1.0,"source_file":"./src/utils/taskUtils.ts","source_location":"L24","weight":1.0},{"source":"src_utils_taskutils_ts","target":"src_utils_taskutils_ts_sorttasks","relation":"defines","confidence":"EXTRACTED","confidence_score":1.0,"source_file":"./src/utils/taskUtils.ts","source_location":"L40","weight":1.0},{"source":"src_utils_taskutils_ts","target":"src_utils_taskutils_ts_grouptasksfortoday","relation":"defines","confidence":"EXTRACTED","confidence_score":1.0,"source_file":"./src/utils/taskUtils.ts","source_location":"L55","weight":1.0},{"source":"src_utils_taskutils_ts","target":"src_utils_taskutils_ts_formattasktime","relation":"defines","confidence":"EXTRACTED","confidence_score":1.0,"source_file":"./src/utils/taskUtils.ts","source_location":"L73","weight":1.0},{"source":"src_utils_taskutils_ts","target":"src_utils_taskutils_ts_matchesstatusfilter","relation":"defines","confidence":"EXTRACTED","confidence_score":1.0,"source_file":"./src/utils/taskUtils.ts","source_location":"L82","weight":1.0},{"source":"src_utils_taskutils_ts","target":"src_utils_taskutils_ts_matchespriorityfilter","relation":"defines","confidence":"EXTRACTED","confidence_score":1.0,"source_file":"./src/utils/taskUtils.ts","source_location":"L86","weight":1.0},{"source":"src_utils_taskutils_ts","target":"src_utils_taskutils_ts_compareoptionalnumber","relation":"defines","confidence":"EXTRACTED","confidence_score":1.0,"source_file":"./src/utils/taskUtils.ts","source_location":"L90","weight":1.0},{"source":"src_utils_taskutils_ts_filtertasks","target":"src_utils_taskutils_ts_gettasktags","relation":"calls","confidence":"INFERRED","confidence_score":0.7,"source_file":"./src/utils/taskUtils.ts","weight":1.0},{"source":"src_utils_taskutils_ts_filtertasks","target":"src_utils_taskutils_ts_matchesstatusfilter","relation":"calls","confidence":"INFERRED","confidence_score":0.7,"source_file":"./src/utils/taskUtils.ts","weight":1.0},{"source":"src_utils_taskutils_ts_filtertasks","target":"src_utils_taskutils_ts_matchespriorityfilter","relation":"calls","confidence":"INFERRED","confidence_score":0.7,"source_file":"./src/utils/taskUtils.ts","weight":1.0},{"source":"src_utils_taskutils_ts_sorttasks","target":"src_utils_taskutils_ts_compareoptionalnumber","relation":"calls","confidence":"INFERRED","confidence_score":0.7,"source_file":"./src/utils/taskUtils.ts","weight":1.0},{"source":"src_utils_taskutils_ts_grouptasksfortoday","target":"src_utils_taskutils_ts_sorttasks","relation":"calls","confidence":"INFERRED","confidence_score":0.7,"source_file":"./src/utils/taskUtils.ts","weight":1.0}],"hyperedges":[]}